dj_core_drf/__init__.py
dj_core_drf/apps.py
dj_core_drf/config.py
dj_core_drf/fields.py
dj_core_drf/metadata.py
dj_core_drf/pagination.py
dj_core_drf/routes.py
dj_core_drf/serializers.py
dj_core_drf/validators.py
dj_core_drf/views.py
dj_core_drf-0.2.1.dist-info/METADATA
dj_core_drf-0.2.1.dist-info/RECORD
dj_core_drf-0.2.1.dist-info/WHEEL
dj_core_drf-0.2.1.dist-info/top_level.txt
